<?xml version="1.0" encoding="utf-8" ?>
<Defs>

  <HediffDef ParentName="WVC_HediffMutation_Base">
	<defName>SpecialHediff_NodeEruption_WVC</defName>
	<label>Node eruption</label>
	<description>The body of this creature is covered with thin lines akin to those found on node cubes.</description>
	<countsAsAddedPartOrImplant>false</countsAsAddedPartOrImplant>
	<defaultLabelColor>(255,248,133)</defaultLabelColor>
	<priceOffset>-5000</priceOffset>
	<stages>
	  <li>
		<statOffsets>
		  <ArmorRating_Sharp>0.1</ArmorRating_Sharp>
		  <ArmorRating_Blunt>0.1</ArmorRating_Blunt>
		  <ArmorRating_Heat>0.1</ArmorRating_Heat>
		  <PawnBeauty>-2</PawnBeauty>
		</statOffsets>
	  </li>
	</stages>
  </HediffDef>

  <!-- ================================================================== -->

  <HediffDef ParentName="WVC_HediffMutation_Base">
	<defName>SpecialHediff_RedNodeModel_WVC</defName>
	<label>Red Nodes: Living Form Integration</label>
	<description>&lt;color=#FF8585&gt;///NO INFORMATION AVAILABLE///&lt;/color&gt;</description>
	<countsAsAddedPartOrImplant>false</countsAsAddedPartOrImplant>
	<defaultLabelColor>(255,133,133)</defaultLabelColor>
	<stages>
	  <li>
		<statOffsets>
			<MeleeDodgeChance>15.0</MeleeDodgeChance>
			<MeleeHitChance>5.0</MeleeHitChance>
		</statOffsets>
		<statFactors>
			<IncomingDamageFactor>0.5</IncomingDamageFactor>
		</statFactors>
	  </li>
	</stages>
  </HediffDef>

  <HediffDef ParentName="WVC_HediffMutation_Base">
	<defName>SpecialHediff_BlueNodeModel_WVC</defName>
	<label>Blue Nodes: Living Form Integration</label>
	<description>&lt;color=#FF8585&gt;///NO INFORMATION AVAILABLE///&lt;/color&gt;</description>
	<countsAsAddedPartOrImplant>false</countsAsAddedPartOrImplant>
	<defaultLabelColor>(133,202,255)</defaultLabelColor>
	<stages>
	  <li>
		<statOffsets>
			<WorkSpeedGlobal>0.2</WorkSpeedGlobal>
			<RestRateMultiplier>0.2</RestRateMultiplier>
		</statOffsets>
		<!-- <statFactors> -->
		<!-- </statFactors> -->
	  </li>
	</stages>
  </HediffDef>

  <HediffDef ParentName="WVC_HediffMutation_Base">
	<defName>SpecialHediff_GreenNodeModel_WVC</defName>
	<label>Green Nodes: Living Form Integration</label>
	<description>&lt;color=#FF8585&gt;///NO INFORMATION AVAILABLE///&lt;/color&gt;</description>
	<countsAsAddedPartOrImplant>false</countsAsAddedPartOrImplant>
	<defaultLabelColor>(133,255,136)</defaultLabelColor>
	<stages>
	  <li>
		<statOffsets>
			<InjuryHealingFactor>0.5</InjuryHealingFactor>
		</statOffsets>
		<statFactors>
			<IncomingDamageFactor>0.9</IncomingDamageFactor>
		</statFactors>
		<!-- <statFactors> -->
		<!-- </statFactors> -->
	  </li>
	</stages>
  </HediffDef>

	<!-- ================================================================== -->

	<AlienRace.BackstoryDef ParentName="Base_HumanoidBackstory_WVC" Name="NodeELFs_HumanoidBackstory_WVC" Abstract="True">
		<!-- <title>&lt;color=#85caff&gt;N&lt;/color&gt;&lt;color=#85ff88&gt;o&lt;/color&gt;&lt;color=#FF8585&gt;d&lt;/color&gt;&lt;color=#8e85ff&gt;e&lt;/color&gt;&lt;color=#FFF885&gt;s&lt;/color&gt;: &lt;color=#a2adff&gt;Living Form&lt;/color&gt;</title> -->
		<title>&lt;color=#FFF885&gt;Nodes: Living Form&lt;/color&gt;</title>
		<titleShort>&lt;color=#FFF885&gt;NLF&lt;/color&gt;</titleShort>
		<baseDescription>Standard &lt;color=#85caff&gt;ELF&lt;/color&gt; model created using node technologies.</baseDescription>
		<forcedHediffs>
		  <li>SpecialHediff_NodeEruption_WVC</li>
		</forcedHediffs>
		<spawnCategories>
		  <li>NodesBackstory_Child_ELFs_WVC</li>
		</spawnCategories>
		<!-- <forcedTraits> -->
			<!-- <li> -->
				<!-- <defName>Valkyrie_Herrschers_WVC</defName> -->
				<!-- <chance>100</chance> -->
			<!-- </li> -->
		<!-- </forcedTraits> -->
		<skillGains Inherit="False">
		  <li>
			<defName>Shooting</defName>
			<amount>4</amount>
		  </li>
		  <li>
			<defName>Melee</defName>
			<amount>4</amount>
		  </li>
		  <li>
			<defName>Medicine</defName>
			<amount>6</amount>
		  </li>
		  <li>
			<defName>Crafting</defName>
			<amount>6</amount>
		  </li>
		  <li>
			<defName>Intellectual</defName>
			<amount>6</amount>
		  </li>
		  <li>
			<defName>Animals</defName>
			<amount>3</amount>
		  </li>
		  <li>
			<defName>Construction</defName>
			<amount>3</amount>
		  </li>
		</skillGains>
	</AlienRace.BackstoryDef>

	<!-- Base -->
	<AlienRace.BackstoryDef ParentName="NodeELFs_HumanoidBackstory_WVC">
		<defName>NodeBackstoryChild_ELF_Base_WVC</defName>
		<baseDescription>Standard &lt;color=#85caff&gt;ELF&lt;/color&gt; model created using node technologies.</baseDescription>
		<slot>Childhood</slot>
	</AlienRace.BackstoryDef>
	<AlienRace.BackstoryDef ParentName="NodeELFs_HumanoidBackstory_WVC">
		<defName>NodeBackstoryAdult_ELF_Base_WVC</defName>
		<title>&lt;color=#FFF885&gt;Advanced software&lt;/color&gt;</title>
		<baseDescription>Advanced self-learning technology and a bit of luck have allowed [PAWN_nameDef] to be a step up from the models in the same series.</baseDescription>
		<!-- <baseDescription>&lt;color=#FF8585&gt;///NO INFORMATION AVAILABLE///&lt;/color&gt;</baseDescription> -->
		<slot>Adulthood</slot>
		<spawnCategories>
		  <li>NodesBackstory_Adult_ELFs_WVC</li>
		</spawnCategories>
	</AlienRace.BackstoryDef>

	<!-- Nodes -->
	<AlienRace.BackstoryDef ParentName="NodeELFs_HumanoidBackstory_WVC">
		<defName>NodeBackstoryChild_ELF_RedNode_WVC</defName>
		<title>&lt;color=#FF8585&gt;Nodes: Living Form&lt;/color&gt;</title>
		<titleShort>&lt;color=#FF8585&gt;NLF&lt;/color&gt;</titleShort>
		<baseDescription>&lt;color=#FF8585&gt;"Red"&lt;/color&gt; model. Advanced military technologies and integrations are at the heart of this &lt;color=#a2adff&gt;ELF&lt;/color&gt; model.</baseDescription>
		<slot>Childhood</slot>
		<forcedHediffs>
		  <li>SpecialHediff_RedNodeModel_WVC</li>
		</forcedHediffs>
		<skillGains Inherit="False">
		  <li>
			<defName>Shooting</defName>
			<amount>12</amount>
		  </li>
		  <li>
			<defName>Melee</defName>
			<amount>12</amount>
		  </li>
		  <li>
			<defName>Medicine</defName>
			<amount>2</amount>
		  </li>
		  <li>
			<defName>Crafting</defName>
			<amount>2</amount>
		  </li>
		  <li>
			<defName>Intellectual</defName>
			<amount>2</amount>
		  </li>
		  <li>
			<defName>Animals</defName>
			<amount>1</amount>
		  </li>
		  <li>
			<defName>Construction</defName>
			<amount>1</amount>
		  </li>
		</skillGains>
	</AlienRace.BackstoryDef>

	<AlienRace.BackstoryDef ParentName="NodeELFs_HumanoidBackstory_WVC">
		<defName>NodeBackstoryChild_ELF_BlueNode_WVC</defName>
		<title>&lt;color=#85caff&gt;Nodes: Living Form&lt;/color&gt;</title>
		<titleShort>&lt;color=#85caff&gt;NLF&lt;/color&gt;</titleShort>
		<baseDescription>&lt;color=#85caff&gt;"Blue"&lt;/color&gt; model. Advanced engineering technologies and integrations are at the heart of this &lt;color=#a2adff&gt;ELF&lt;/color&gt; model.</baseDescription>
		<slot>Childhood</slot>
		<forcedHediffs>
		  <li>SpecialHediff_BlueNodeModel_WVC</li>
		</forcedHediffs>
		<skillGains Inherit="False">
		  <li>
			<defName>Shooting</defName>
			<amount>-2</amount>
		  </li>
		  <li>
			<defName>Melee</defName>
			<amount>-2</amount>
		  </li>
		  <li>
			<defName>Medicine</defName>
			<amount>3</amount>
		  </li>
		  <li>
			<defName>Crafting</defName>
			<amount>12</amount>
		  </li>
		  <li>
			<defName>Intellectual</defName>
			<amount>8</amount>
		  </li>
		  <li>
			<defName>Animals</defName>
			<amount>1</amount>
		  </li>
		  <li>
			<defName>Construction</defName>
			<amount>10</amount>
		  </li>
		</skillGains>
	</AlienRace.BackstoryDef>

	<AlienRace.BackstoryDef ParentName="NodeELFs_HumanoidBackstory_WVC">
		<defName>NodeBackstoryChild_ELF_GreenNode_WVC</defName>
		<title>&lt;color=#85ff88&gt;Nodes: Living Form&lt;/color&gt;</title>
		<titleShort>&lt;color=#85ff88&gt;NLF&lt;/color&gt;</titleShort>
		<baseDescription>&lt;color=#85ff88&gt;"Green"&lt;/color&gt; model. Advanced medical technologies and integrations are at the heart of this &lt;color=#a2adff&gt;ELF&lt;/color&gt; model.</baseDescription>
		<slot>Childhood</slot>
		<forcedHediffs>
		  <li>SpecialHediff_GreenNodeModel_WVC</li>
		</forcedHediffs>
		<skillGains Inherit="False">
		  <li>
			<defName>Shooting</defName>
			<amount>-6</amount>
		  </li>
		  <li>
			<defName>Melee</defName>
			<amount>-6</amount>
		  </li>
		  <li>
			<defName>Medicine</defName>
			<amount>12</amount>
		  </li>
		  <li>
			<defName>Crafting</defName>
			<amount>2</amount>
		  </li>
		  <li>
			<defName>Intellectual</defName>
			<amount>12</amount>
		  </li>
		  <li>
			<defName>Animals</defName>
			<amount>4</amount>
		  </li>
		  <li>
			<defName>Construction</defName>
			<amount>2</amount>
		  </li>
		</skillGains>
	</AlienRace.BackstoryDef>
  
</Defs>
